MANIFEST.in
README.md
requirements.txt
setup.cfg
setup.py
google/__init__.py
google/api.py
google/exceptions.py
google_python_sdk.egg-info/PKG-INFO
google_python_sdk.egg-info/SOURCES.txt
google_python_sdk.egg-info/dependency_links.txt
google_python_sdk.egg-info/requires.txt
google_python_sdk.egg-info/top_level.txt