Metadata-Version: 1.1
Name: google-python-sdk
Version: 1.0.0
Summary: Python Google API
Home-page: https://github.com/rohitkhatri/google-python-sdk
Author: Rohit Khatri
Author-email: developer.rohitkhatri@gmail.com
License: GPL
Keywords: google data api python
Platform: UNKNOWN
Classifier: Development Status :: 4 - Beta
Classifier: Intended Audience :: Developers
Classifier: Operating System :: OS Independent
Classifier: Programming Language :: Python :: 3.5
Classifier: Operating System :: OS Independent
Classifier: Topic :: Software Development :: Libraries :: Python Modules
